odoo8_addon_l10n_it_fatturapa_out_stamp-8.0.2.0.0-nspkg.pth
odoo_addons/l10n_it_fatturapa_out_stamp/README.rst
odoo_addons/l10n_it_fatturapa_out_stamp/__init__.py
odoo_addons/l10n_it_fatturapa_out_stamp/__openerp__.py
odoo_addons/l10n_it_fatturapa_out_stamp/i18n/l10n_it_fatturapa_out_stamp.pot
odoo_addons/l10n_it_fatturapa_out_stamp/readme/CONTRIBUTORS.rst
odoo_addons/l10n_it_fatturapa_out_stamp/readme/DESCRIPTION.rst
odoo_addons/l10n_it_fatturapa_out_stamp/static/description/icon.png
odoo_addons/l10n_it_fatturapa_out_stamp/static/description/index.html
odoo_addons/l10n_it_fatturapa_out_stamp/wizard/__init__.py
odoo_addons/l10n_it_fatturapa_out_stamp/wizard/wizard_export_fatturapa.py
odoo8_addon_l10n_it_fatturapa_out_stamp-8.0.2.0.0.dist-info/METADATA
odoo8_addon_l10n_it_fatturapa_out_stamp-8.0.2.0.0.dist-info/WHEEL
odoo8_addon_l10n_it_fatturapa_out_stamp-8.0.2.0.0.dist-info/namespace_packages.txt
odoo8_addon_l10n_it_fatturapa_out_stamp-8.0.2.0.0.dist-info/top_level.txt
odoo8_addon_l10n_it_fatturapa_out_stamp-8.0.2.0.0.dist-info/RECORD
